{
  "assetsByChunkName": {
    "vendors~app-account~app-confirmation~app-order": "chunk.8b48014d402f6a25c96c.js",
    "vendors~app-account~app-checkout": "chunk.fd3aa05a98a84abd99c3.js",
    "vendors~app-cart~app-checkout": "chunk.2f2baf58ad2ce3d506da.js",
    "ProductVariations": "ProductVariations.7e5c0107c0aa99e55559.js",
    "admin": [
      "admin.f22ce72d6c2a5ccb8937.js",
      "admin.f22ce72d6c2a5ccb8937.js.map"
    ],
    "app-account": "chunk.050e392f86573eedde51.js",
    "app-confirmation": "chunk.aedc173889c1d4931fdc.js",
    "app-order": "chunk.e67152fbcea55c573791.js",
    "checkout": [
      "checkout.412ea25dd02342283a20.js",
      "checkout.412ea25dd02342283a20.js.map"
    ],
    "storefront": [
      "storefront.402a0a45817640fc3fdf.css",
      "storefront.06762a7f7dc1955355ea.js",
      "storefront.402a0a45817640fc3fdf.css.map",
      "storefront.06762a7f7dc1955355ea.js.map"
    ],
    "vendors~app-cart": "chunk.ef0e580f13dd999d0586.js",
    "vendors~app-checkout": "chunk.8bde9f88e891f33ed095.js"
  }
}